noun_hound-1.0.0.dist-info/METADATA
noun_hound-1.0.0.dist-info/top_level.txt
noun_hound-1.0.0.dist-info/metadata.json
noun_hound-1.0.0.dist-info/DESCRIPTION.rst
noun_hound-1.0.0.dist-info/WHEEL
noun_hound-1.0.0.dist-info/RECORD
noun_hound/__init__.py
noun_hound/noun_hound.py
noun_hound/pickles/tagger.pkl
