Metadata-Version: 2.0
Name: noun-hound
Version: 1.0.0
Summary: Finds nouns and noun phrases in given text.
Home-page: https://github.com/lettier/noun_hound
Author: Lettier
Author-email: noun_hound@lettier.com
License: Apache License, Version 2.0
Keywords: nlp natural language processing phrase extraction chunking
Platform: UNKNOWN
Classifier: Development Status :: 5 - Production/Stable
Classifier: Intended Audience :: Developers
Classifier: License :: OSI Approved :: Apache Software License
Classifier: Programming Language :: Python :: 2.7
Classifier: Programming Language :: Python :: 3.2
Classifier: Programming Language :: Python :: 3.3
Classifier: Programming Language :: Python :: 3.4
Classifier: Topic :: Text Processing
Requires-Dist: nltk
Requires-Dist: future
Provides-Extra: dev
Provides-Extra: test
